Midterm_SPI_Interface/d_ff.v
/*
Module name: D flipflop
CLR : k đồng bộ, đặt ngõ ra mức 0 khi CLR = 1, còn lại 0,z thì k tác động
PRE : k đồng bộ, đặt ngõ ra mức 1 khi PRE = 1, còn lại 0,z thì k tác động
NOTE: Khi cả posedge CLK, CLR, PRE cùng tác động thì ưu tiên CLR, PRE
*/

module d_ff(output reg Q, input DATA, input CLK, input CLR, input PRE);
    //posedge for "low-to-high edge"
    //negedge for "high-to-low edge"
    initial begin // vô kiểm tra bỏ qua cái này nhe :v
        Q = 1'b0;
        end
    always @(CLR, PRE)
        begin
            if( CLR == 1'b0 && PRE == 1'b0)
                Q = Q;
            else if(CLR == 1'b1 && PRE == 1'b0)
                Q = 1'b0;
            else if(CLR == 1'b0 && PRE == 1'b1)
                Q = 1'b1;
            else Q = Q;
        end
    always @(posedge CLK)
        begin
            if( CLR == 1'b0 && PRE == 1'b0)
                Q = DATA;
            else if(CLR == 1'b1 && PRE == 1'b0)
                Q = 1'b0;
            else if(CLR == 1'b0 && PRE == 1'b1)
                Q = 1'b1;
            else Q = Q;
        end
endmodule

Midterm_SPI_Interface/shift_register_4bit.v
/*
    Thanh ghi dịch 8bit
    Ngõ vào:
        - Xung CLK 
        - CLEAR : đạt toàn bộ ngõ ra trong thanh ghi dịch về 0
        - [4] P_DATA_IN : giá trị để đặt trước (vào song song)
        - S_DATA_IN : vào nối tiếp
        - SH_LD : đặt trước giá trị hoặc dịch
            + SH_LD = 0, ngưng dịch, vào song song (bằng cách động vào chân CLR, PRE của từng FF-D)
            + SH_LD = 1, dịch
    Ngõ ra
        - [4] P_DATA_OUT : kết nối tới từng FF-D bên trong
*/

`include "d_ff.v"

module SHIFT_REGISTER_4BIT (
    input CLK,
    input CLR,
    input [3:0] P_DATA_IN,
    input S_DATA_IN,
    input SH_LD,
    output  [3:0] P_DATA_OUT
);
    //Khai báo dây d?n bên trong
    wire notSH_LD;
    wire notCLR;
    wire [3:0]D_CLR;// tín hi?u cu?i cùng d?n d-ff (tín hi?u clr theo data set-up ho?c bu?c reset)
    wire [3:0]S_CLR;// tín hi?u t? DATA set-up
    wire [3:0]D_DATA;// dây d?n n?i d?n chân D c?a t?ng d-ff
    wire [3:0]D_PRE;
    wire [3:0]S_PRE;
    
    d_ff dff0 (.CLK(CLK), .CLR(D_CLR[0]), .PRE(D_PRE[0]), .DATA(S_DATA_IN),     .Q(P_DATA_OUT[3]) );
    d_ff dff1 (.CLK(CLK), .CLR(D_CLR[1]), .PRE(D_PRE[1]), .DATA(P_DATA_OUT[3]), .Q(P_DATA_OUT[2]) );
    d_ff dff2 (.CLK(CLK), .CLR(D_CLR[2]), .PRE(D_PRE[2]), .DATA(P_DATA_OUT[2]), .Q(P_DATA_OUT[1]) );
    d_ff dff3 (.CLK(CLK), .CLR(D_CLR[3]), .PRE(D_PRE[3]), .DATA(P_DATA_OUT[1]), .Q(P_DATA_OUT[0]) );

    not(notSH_LD, SH_LD);
    // assign notSH_LD=SH_LD;
    not(notCLR, CLR);

    and(S_PRE[0], notSH_LD, D_DATA[3]); nor(S_CLR[0], SH_LD, D_DATA[3]);
    and(S_PRE[1], notSH_LD, D_DATA[2]); nor(S_CLR[1], SH_LD, D_DATA[2]);
    and(S_PRE[2], notSH_LD, D_DATA[1]); nor(S_CLR[2], SH_LD, D_DATA[1]);
    and(S_PRE[3], notSH_LD, D_DATA[0]); nor(S_CLR[3], SH_LD, D_DATA[0]);

    and(D_PRE[0], S_PRE[0], notCLR); or(D_CLR[0], S_CLR[0], CLR);
    and(D_PRE[1], S_PRE[1], notCLR); or(D_CLR[1], S_CLR[1], CLR);
    and(D_PRE[2], S_PRE[2], notCLR); or(D_CLR[2], S_CLR[2], CLR);
    and(D_PRE[3], S_PRE[3], notCLR); or(D_CLR[3], S_CLR[3], CLR);


    assign D_DATA = P_DATA_IN;
    // assign D_DATA = (SH_LD==0)?(P_DATA_IN):(4'bzzzz); // cách ly ngõ vào thi?t l?p c?a t?ng FF-D v?i ngõ vào song song khi không có tín hi?u LD (load)

endmodule

Midterm_SPI_Interface/shift_register_8bit.v

`include "shift_register_4bit.v"

module SHIFT_REGISTER_8BIT (
    input CLK,
    input CLR,
    input [7:0] P_DATA_IN,
    input S_DATA_IN,
    input SH_LD,
    output[7:0] P_DATA_OUT
);

    SHIFT_REGISTER_4BIT shift_register_0(
        .CLK(CLK),
        .CLR(CLR),
        .P_DATA_IN(P_DATA_IN[7:4]),
        .S_DATA_IN(S_DATA_IN),
        .SH_LD(SH_LD),
        .P_DATA_OUT(P_DATA_OUT[7:4])
    );
    SHIFT_REGISTER_4BIT shift_register_1(
        .CLK(CLK),
        .CLR(CLR),
        .P_DATA_IN(P_DATA_IN[3:0]),
        .S_DATA_IN(P_DATA_OUT[4]),
        .SH_LD(SH_LD),
        .P_DATA_OUT(P_DATA_OUT[3:0])
    );
endmodule

Midterm_SPI_Interface/sender_receiver.v
`timescale 100ps/100ps
`include "shift_register_8bit.v" //nhập mô-đun 

/*
Module name: sender
Ngõ vào:
    bus 8 dây DATA  : dữ liệu vào song song  (ghi bởi controller)
    CLR : xoá hết thanh ghi, đặt FULL về 0
    WRITE  : Ghi, WRITE = 1 ghi, WRITE = 0 dịch
        *Chế độ ghi, đồng bộ với xung SCLK, WRITE = 1: 
            + Ngưng dịch
            + Set trạng thái của thanh ghi theo trạng thái ngõ vào [7:0] DATA
        *Chế độ dịch WRITE = 0:
            + [7:0] DATA ở trạng thái trở kháng cao?????
            + Dịch ngõ vào SER theo điều khiển của TE
            + Dịch ngõ ra MOSI theo điều khiển của TE
    TE (Transfering-enable) : Cho phép gởi khi TE = 1, khoá xung CLK đến thanh ghi dịch khi TE = 0
Ngõ ra:
    MOSI : Dữ liệu ra nối tiếp theo SCLK
    FULL_STATE : 1 - thanh ghi đầy (khi chưa gởi đi bit nào)
    EMPTY_STATE : 1 - khi đã gởi hết 8 bit

*/

module sender (
    input [7:0] DATA, 
    input CLR,
    input WRITE,
    input TE,
    input CLK,
    output MOSI, 
    output FULL_STATE, 
    output EMPTY_STATE 
);
    wire [7:0] P_DATA_OUT;//dây n?i 8 chân ngõ ra song song c?a thanh ghi d?ch
    reg [3:0] COUNT_SENT;//d?m s? bit dã g?i, ki?m soát tr?ng thái r?ng/d?y c?a thanh ghi d?ch
    reg SHIFT_CLK;//dây n?i d?n chân CLK c?a thanh ghi d?ch
    wire LOW, HIGH;

    initial begin
        COUNT_SENT = 4'b1000;//d?n s? li?u d? dã g?i, ban d?u thanh ghi r?ng!
    end

    SHIFT_REGISTER_8BIT sender_shift_register(
        .CLK(SHIFT_CLK),
        .CLR(CLR),
        .P_DATA_IN(DATA),
        .S_DATA_IN(LOW),
        .SH_LD(~WRITE),
        .P_DATA_OUT(P_DATA_OUT)
    );

    always @(SHIFT_CLK, CLR, WRITE)
        if(CLR == 1)
            COUNT_SENT = 4'b1000;
        else if(WRITE == 1)
				 COUNT_SENT = 4'b0000;
				 else if(TE == HIGH && EMPTY_STATE == LOW)
                  COUNT_SENT = COUNT_SENT + 1;
    always @(CLK)
        SHIFT_CLK = #5 CLK & TE;

    assign LOW = 1'b0;
    assign HIGH = 1'b1;  
    // assign SHIFT_CLK = #1 CLK & TE & (~EMPTY_STATE);
    assign MOSI = (TE == HIGH)?(P_DATA_OUT[0]):(LOW);
    assign EMPTY_STATE = (COUNT_SENT == 4'b1000) ? HIGH : LOW;
    assign FULL_STATE = ((COUNT_SENT == 4'b0000))? HIGH : LOW;
endmodule     



//--------------------------------------------------------------------------------------------------
/*
Module name: receiver
Ngõ vào:
    MISO: dữ liệu nhận về, dịch vào thanh ghi
    CLR : xoá hết thanh ghi, FULL_STATE=0, EMPTY_STATE=1
    READ  : Đọc, READ = 1 đọc, READ = 0 dịch dữ liệu vào
        *Chế độ đọc, đồng bộ với xung SCLK, READ = 1: 
            + Ngưng dịch
            + Set trạng thái của [7:0] DATA thành trạng thái của 8 ngõ ra thanh ghi
        *Chế độ dịch READ = 0:
            + [7:0] DATA ở trạng thái trở kháng cao?????
            + Dịch ngõ vào MISO theo điều khiển của RE
            + Dịch ngõ ra MOSI theo điều khiển của RE
    RE (Receiving-enable) : Cho phép nhận khi RE = 1, khoá xung CLK đến thanh ghi dịch khi RE = 0
Ngõ ra:
    DATA[7:0] : Dữ liệu ra song song (đọc bởi controller)
    FULL_STATE : 1 - thanh ghi đầy (đã nhận đủ 8bit)
    EMPTY_STATE : 1 - thi ghi rỗng (chưa nhận được bit nào)
*/

module receiver (
    input CLR,
    input READ,
    input RE,
    input MISO,
    input CLK,
    output [7:0]DATA,
    output FULL_STATE, 
    output EMPTY_STATE 
);
    wire LOW, HIGH;
    wire [7:0] P_DATA_OUT;//dây n?i 8 chân ngõ ra song song c?a thanh ghi d?ch
    reg [3:0] COUNT_RECEIVED;//d?m s? bit dã nh?n
    reg SHIFT_CLK;//dây n?i d?n chân CLK c?a thanh ghi d?ch

    initial begin
        COUNT_RECEIVED = 0;//d?n s? li?u d? dã nh?n
    end

    SHIFT_REGISTER_8BIT receiver_shift_register (
        .CLK(SHIFT_CLK),
        .CLR(CLR),
        .P_DATA_IN(8'bzzzz_zzzz),//d? tr?ng vì không s? d?ng
        .S_DATA_IN(MISO),
        .SH_LD(HIGH),//luôn ? tr?ng thái d?ch, di?u khi?n b?ng xung CLK
        .P_DATA_OUT(P_DATA_OUT)
    );

    always @(SHIFT_CLK, CLR, READ)
        if(CLR == HIGH || READ == HIGH)
            COUNT_RECEIVED = 4'b0000; // chua nh?n bit nào = r?ng
        else
            if( RE & (~FULL_STATE) & (~READ) == HIGH ) //v?n cho phép nh?n và chua d?y
                COUNT_RECEIVED = COUNT_RECEIVED + 4'b0001;

    always @(CLK)
        SHIFT_CLK = #5 CLK & RE & (~FULL_STATE) & (~READ);
    //Có thêm (~READ) d? khoá xung vì ho?t d?ng d?c k tác d?ng d?n các FF-D 
    //bên trong thanh ghi và ph?i khoá xung clk n?u k d? li?u s? thay d?i
    //và không d?c du?c
    //Khác v?i ho?t d?ng ghi, ho?t d?ng này can thi?p vào các FF-D bên trong
    //thanh ghi d?ch thông qua các chân PRE,CLR nên không b? ?nh hu?ng 
    //b?i xung CLK
    assign LOW = 1'b0;
    assign HIGH = 1'b1;  
    assign EMPTY_STATE        = (COUNT_RECEIVED == 4'B0000)?(HIGH):(LOW);
    assign FULL_STATE         = (COUNT_RECEIVED == 4'B1000)?(HIGH):(LOW);
    assign DATA               = (READ==1)?(P_DATA_OUT):(8'bzzzz_zzzz);
endmodule

Midterm_SPI_Interface/clk_generator.v
`timescale 1ns/1ns
module clk_gen(
    output clk
);
    reg [7:0] c;
    initial begin
        c = 0;
        #5;
        for( c = 0; c < 8'b11111111; c=c+1)
            #5;
    end

    assign clk = c[0];
endmodule

Midterm_SPI_Interface/test_module.v
/*
Module name: Only using for show wave
Author: Nguyen Thanh Phu
*/
`timescale 1ns/1ns
`include "sender_receiver.v"
`include "clk_generator.v"

module show_wave;
    reg[7:0] DATA_IN;
    reg CLR = 0;
    reg WRITE = 0;
    reg READ = 0;
    reg TE = 0;
    reg RE = 0;
    wire MOSI;
    wire MISO;
    wire S_FULL_STATE;
    wire S_EMPTY_STATE;
    wire R_FULL_STATE;
    wire R_EMPTY_STATE;
    wire clk_out;
    wire [7:0] DATA_OUT;

    clk_gen clk_gen_ins(.clk(clk_out));

    sender sender_test(
        .DATA(DATA_IN), 
        .CLR(CLR),
        .WRITE(WRITE),
        .TE(TE),
        .CLK(clk_out),
        .MOSI(MOSI), 
        .FULL_STATE(S_FULL_STATE), 
        .EMPTY_STATE(S_EMPTY_STATE)
    );
    receiver receiver_test(
        .CLR(CLR),
        .READ(READ),
        .RE(RE),
        .MISO(MISO),
        .CLK(clk_out),
        .DATA(DATA_OUT),
        .FULL_STATE(R_FULL_STATE), 
        .EMPTY_STATE(R_EMPTY_STATE)
    );

    assign MISO = MOSI;

initial begin
    $dumpfile("show_wave.vcd"); 
    $dumpvars(0, show_wave);

    //---------------- Tr?ng thái ban d?u
    DATA_IN = 8'b0100_0011;
    #20;
    //---------------- Nh?n CLR
    CLR = 0;
    CLR = 1 ; #10;
    CLR = 0;
    //---------------- Ghi d? li?u lên thanh ghi
    WRITE = 1;
    #10;
    WRITE = 0;
    //---------------- R?i, k ghi, k truy?n
    #20
    DATA_IN = 8'b0101_1111;
    WRITE = 1;
    #10;
    WRITE = 0;
    #20;
    //---------------- Truy?n d? li?u
    TE = 1; RE = 1;
    #80;

    #30;
    TE = 0; RE = 0;
    //---------------- R?i
    #30;
    //---------------- Ð?c d? li?u t? receiver
    READ = 1;
    #20;
    READ = 0;
    //---------------- xoá thanh ghi hai bên
    CLR = 1;
    #10;
    CLR = 0;
    //---------------- Ghi d? li?u chu?n b? g?i
    WRITE = 1;
    #7;
    WRITE = 0;
    #9
    //---------------- G?i d? li?u, nhung bên nh?n chua k ch?p nh?n
    TE = 1; RE = 1;
    #30;
    RE = 1;
    #50;

    #30;
    TE = 0; RE = 0;
    //---------------- Th? d?c d? li?u
    READ = 1;
    #20;
    READ = 0;
    //----------------
    $display("Test completed!");
end
endmodule

/*
iverilog -o show_wave.vvp show_wave.v; vvp show_wave.vvp; gtkwave show_wave.vcd
*/

Midterm_SPI_Interface/build/show_wave.vcd
$date
	Thu Apr 11 00:28:48 2024
$end
$version
	Icarus Verilog
$end
$timescale
	100ps
$end
$scope module show_wave $end
$var wire 1 ! MISO $end
$var wire 1 " clk_out $end
$var wire 1 # S_FULL_STATE $end
$var wire 1 $ S_EMPTY_STATE $end
$var wire 1 % R_FULL_STATE $end
$var wire 1 & R_EMPTY_STATE $end
$var wire 1 ' MOSI $end
$var wire 8 ( DATA_OUT [7:0] $end
$var reg 1 ) CLR $end
$var reg 8 * DATA_IN [7:0] $end
$var reg 1 + RE $end
$var reg 1 , READ $end
$var reg 1 - TE $end
$var reg 1 . WRITE $end
$scope module clk_gen_ins $end
$var wire 1 " clk $end
$var reg 8 / c [7:0] $end
$upscope $end
$scope module receiver_test $end
$var wire 1 " CLK $end
$var wire 1 ) CLR $end
$var wire 1 0 HIGH $end
$var wire 1 1 LOW $end
$var wire 1 ! MISO $end
$var wire 1 + RE $end
$var wire 1 , READ $end
$var wire 8 2 P_DATA_OUT [7:0] $end
$var wire 1 % FULL_STATE $end
$var wire 1 & EMPTY_STATE $end
$var wire 8 3 DATA [7:0] $end
$var reg 4 4 COUNT_RECEIVED [3:0] $end
$var reg 1 5 SHIFT_CLK $end
$scope module receiver_shift_register $end
$var wire 1 5 CLK $end
$var wire 1 ) CLR $end
$var wire 8 6 P_DATA_IN [7:0] $end
$var wire 1 0 SH_LD $end
$var wire 1 ! S_DATA_IN $end
$var wire 8 7 P_DATA_OUT [7:0] $end
$scope module shift_register_0 $end
$var wire 1 5 CLK $end
$var wire 1 ) CLR $end
$var wire 4 8 D_DATA [3:0] $end
$var wire 4 9 P_DATA_IN [3:0] $end
$var wire 1 0 SH_LD $end
$var wire 1 ! S_DATA_IN $end
$var wire 1 : notCLR $end
$var wire 1 ; notSH_LD $end
$var wire 4 < S_PRE [3:0] $end
$var wire 4 = S_CLR [3:0] $end
$var wire 4 > P_DATA_OUT [3:0] $end
$var wire 4 ? D_PRE [3:0] $end
$var wire 4 @ D_CLR [3:0] $end
$scope module dff0 $end
$var wire 1 5 CLK $end
$var wire 1 A CLR $end
$var wire 1 ! DATA $end
$var wire 1 B PRE $end
$var reg 1 C Q $end
$upscope $end
$scope module dff1 $end
$var wire 1 5 CLK $end
$var wire 1 D CLR $end
$var wire 1 E DATA $end
$var wire 1 F PRE $end
$var reg 1 G Q $end
$upscope $end
$scope module dff2 $end
$var wire 1 5 CLK $end
$var wire 1 H CLR $end
$var wire 1 I DATA $end
$var wire 1 J PRE $end
$var reg 1 K Q $end
$upscope $end
$scope module dff3 $end
$var wire 1 5 CLK $end
$var wire 1 L CLR $end
$var wire 1 M DATA $end
$var wire 1 N PRE $end
$var reg 1 O Q $end
$upscope $end
$upscope $end
$scope module shift_register_1 $end
$var wire 1 5 CLK $end
$var wire 1 ) CLR $end
$var wire 4 P D_DATA [3:0] $end
$var wire 4 Q P_DATA_IN [3:0] $end
$var wire 1 0 SH_LD $end
$var wire 1 R S_DATA_IN $end
$var wire 1 S notCLR $end
$var wire 1 T notSH_LD $end
$var wire 4 U S_PRE [3:0] $end
$var wire 4 V S_CLR [3:0] $end
$var wire 4 W P_DATA_OUT [3:0] $end
$var wire 4 X D_PRE [3:0] $end
$var wire 4 Y D_CLR [3:0] $end
$scope module dff0 $end
$var wire 1 5 CLK $end
$var wire 1 Z CLR $end
$var wire 1 R DATA $end
$var wire 1 [ PRE $end
$var reg 1 \ Q $end
$upscope $end
$scope module dff1 $end
$var wire 1 5 CLK $end
$var wire 1 ] CLR $end
$var wire 1 ^ DATA $end
$var wire 1 _ PRE $end
$var reg 1 ` Q $end
$upscope $end
$scope module dff2 $end
$var wire 1 5 CLK $end
$var wire 1 a CLR $end
$var wire 1 b DATA $end
$var wire 1 c PRE $end
$var reg 1 d Q $end
$upscope $end
$scope module dff3 $end
$var wire 1 5 CLK $end
$var wire 1 e CLR $end
$var wire 1 f DATA $end
$var wire 1 g PRE $end
$var reg 1 h Q $end
$upscope $end
$upscope $end
$upscope $end
$upscope $end
$scope module sender_test $end
$var wire 1 " CLK $end
$var wire 1 ) CLR $end
$var wire 8 i DATA [7:0] $end
$var wire 1 j HIGH $end
$var wire 1 k LOW $end
$var wire 1 - TE $end
$var wire 1 . WRITE $end
$var wire 8 l P_DATA_OUT [7:0] $end
$var wire 1 ' MOSI $end
$var wire 1 # FULL_STATE $end
$var wire 1 $ EMPTY_STATE $end
$var reg 4 m COUNT_SENT [3:0] $end
$var reg 1 n SHIFT_CLK $end
$scope module sender_shift_register $end
$var wire 1 n CLK $end
$var wire 1 ) CLR $end
$var wire 8 o P_DATA_IN [7:0] $end
$var wire 1 p SH_LD $end
$var wire 1 k S_DATA_IN $end
$var wire 8 q P_DATA_OUT [7:0] $end
$scope module shift_register_0 $end
$var wire 1 n CLK $end
$var wire 1 ) CLR $end
$var wire 4 r D_DATA [3:0] $end
$var wire 4 s P_DATA_IN [3:0] $end
$var wire 1 p SH_LD $end
$var wire 1 k S_DATA_IN $end
$var wire 1 t notCLR $end
$var wire 1 u notSH_LD $end
$var wire 4 v S_PRE [3:0] $end
$var wire 4 w S_CLR [3:0] $end
$var wire 4 x P_DATA_OUT [3:0] $end
$var wire 4 y D_PRE [3:0] $end
$var wire 4 z D_CLR [3:0] $end
$scope module dff0 $end
$var wire 1 n CLK $end
$var wire 1 { CLR $end
$var wire 1 k DATA $end
$var wire 1 | PRE $end
$var reg 1 } Q $end
$upscope $end
$scope module dff1 $end
$var wire 1 n CLK $end
$var wire 1 ~ CLR $end
$var wire 1 !" DATA $end
$var wire 1 "" PRE $end
$var reg 1 #" Q $end
$upscope $end
$scope module dff2 $end
$var wire 1 n CLK $end
$var wire 1 $" CLR $end
$var wire 1 %" DATA $end
$var wire 1 &" PRE $end
$var reg 1 '" Q $end
$upscope $end
$scope module dff3 $end
$var wire 1 n CLK $end
$var wire 1 (" CLR $end
$var wire 1 )" DATA $end
$var wire 1 *" PRE $end
$var reg 1 +" Q $end
$upscope $end
$upscope $end
$scope module shift_register_1 $end
$var wire 1 n CLK $end
$var wire 1 ) CLR $end
$var wire 4 ," D_DATA [3:0] $end
$var wire 4 -" P_DATA_IN [3:0] $end
$var wire 1 p SH_LD $end
$var wire 1 ." S_DATA_IN $end
$var wire 1 /" notCLR $end
$var wire 1 0" notSH_LD $end
$var wire 4 1" S_PRE [3:0] $end
$var wire 4 2" S_CLR [3:0] $end
$var wire 4 3" P_DATA_OUT [3:0] $end
$var wire 4 4" D_PRE [3:0] $end
$var wire 4 5" D_CLR [3:0] $end
$scope module dff0 $end
$var wire 1 n CLK $end
$var wire 1 6" CLR $end
$var wire 1 ." DATA $end
$var wire 1 7" PRE $end
$var reg 1 8" Q $end
$upscope $end
$scope module dff1 $end
$var wire 1 n CLK $end
$var wire 1 9" CLR $end
$var wire 1 :" DATA $end
$var wire 1 ;" PRE $end
$var reg 1 <" Q $end
$upscope $end
$scope module dff2 $end
$var wire 1 n CLK $end
$var wire 1 =" CLR $end
$var wire 1 >" DATA $end
$var wire 1 ?" PRE $end
$var reg 1 @" Q $end
$upscope $end
$scope module dff3 $end
$var wire 1 n CLK $end
$var wire 1 A" CLR $end
$var wire 1 B" DATA $end
$var wire 1 C" PRE $end
$var reg 1 D" Q $end
$upscope $end
$upscope $end
$upscope $end
$upscope $end
$upscope $end
$enddefinitions $end
$comment Show the parameter values. $end
$dumpall
$end
#0
$dumpvars
0D"
0C"
0B"
0A"
0@"
0?"
0>"
0="
0<"
0;"
0:"
09"
08"
07"
06"
b0 5"
b0 4"
b0 3"
b0 2"
b0 1"
00"
1/"
0."
b11 -"
b11 ,"
0+"
0*"
0)"
0("
0'"
0&"
0%"
0$"
0#"
0""
0!"
0~
0}
0|
0{
b0 z
b0 y
b0 x
b0 w
b0 v
0u
1t
b100 s
b100 r
b0 q
1p
b1000011 o
xn
b1000 m
b0 l
0k
1j
b1000011 i
0h
0g
0f
0e
0d
0c
0b
0a
0`
0_
0^
0]
0\
0[
0Z
b0 Y
b0 X
b0 W
b0 V
b0 U
0T
1S
0R
bz Q
bz P
0O
0N
0M
0L
0K
0J
0I
0H
0G
0F
0E
0D
0C
0B
0A
b0 @
b0 ?
b0 >
b0 =
b0 <
0;
1:
bz 9
bz 8
b0 7
bz 6
x5
b0 4
bz 3
b0 2
01
10
b0 /
0.
0-
0,
0+
b1000011 *
0)
bz (
0'
1&
0%
1$
0#
0"
0!
$end
#5
05
0n
#50
1"
b1 /
#100
0"
b10 /
#150
1"
b11 /
#200
1A
1D
1H
1L
1Z
1]
1a
1e
1{
1~
1$"
1("
16"
19"
1="
1A"
0"
0:
b1111 @
0S
b1111 Y
0t
b1111 z
0/"
b1111 5"
b100 /
1)
#250
1"
b101 /
#300
1""
1?"
1C"
b10 y
b1100 4"
b10 v
b1100 1"
1u
b1101 w
10"
b11 2"
0A
0D
0H
0L
0Z
0]
0a
0e
0$
1#
1{
0~
1$"
1("
16"
19"
0="
0A"
0"
0p
1:
b0 @
1S
b0 Y
b0 m
1t
b1101 z
1/"
b11 5"
b110 /
1.
0)
#305
1%"
1B"
b100 x
1#"
1@"
b1000011 l
b1000011 q
b11 3"
1D"
#350
1"
b111 /
#400
0""
0?"
0C"
b0 y
0{
0$"
0("
b0 4"
06"
09"
b0 z
b0 5"
b0 v
b0 1"
0u
b0 w
00"
b0 2"
0"
1p
b1000 /
0.
#450
1"
b1001 /
#500
0"
b1010 /
#550
1"
b1011 /
#600
1""
1?"
1C"
1*"
17"
1;"
1{
1$"
b1010 y
b1111 4"
b101 z
b1010 v
b1111 1"
1u
b101 w
10"
0"
0p
b101 r
b101 s
b1111 ,"
b1111 -"
b1100 /
1.
b1011111 *
b1011111 i
b1011111 o
#605
1."
1:"
1>"
b101 x
1+"
18"
b1011111 l
b1011111 q
b1111 3"
1<"
#650
1"
b1101 /
#700
0""
0*"
07"
0;"
0?"
0C"
b0 y
0{
0$"
b0 4"
b0 z
b0 v
b0 1"
0u
b0 w
00"
0"
1p
b1110 /
0.
#750
1"
b1111 /
#800
0"
b10000 /
#850
1"
b10001 /
#900
1!
1'
0"
b10010 /
1+
1-
#950
1"
b10011 /
#955
0%"
1)"
0."
0#
1E
0&
0#"
1'"
b101111 l
b101111 q
b10 x
0+"
b1 m
b10000000 2
b10000000 7
b1000 >
1C
b1 4
1n
15
#1000
0"
b10100 /
#1005
b10 4
b10 m
05
0n
#1050
1"
b10101 /
#1055
0)"
1."
0:"
1I
0'"
b1 x
1+"
b10111 l
b10111 q
b111 3"
08"
b11 m
b11000000 2
b11000000 7
b1100 >
1G
b11 4
1n
15
#1100
0"
b10110 /
#1105
b100 4
b100 m
05
0n
#1150
1"
b10111 /
#1155
0."
1:"
0>"
1M
b0 x
0+"
18"
b1011 l
b1011 q
b1011 3"
0<"
b101 m
b11100000 2
b11100000 7
b1110 >
1K
b101 4
1n
15
#1200
0"
b11000 /
#1205
b110 4
b110 m
05
0n
#1250
1"
b11001 /
#1255
0:"
1>"
0B"
1R
08"
1<"
b101 l
b101 q
b101 3"
0@"
b111 m
b11110000 2
b11110000 7
b1111 >
1O
b111 4
1n
15
#1300
0"
b11010 /
#1305
1%
1$
b1000 4
b1000 m
05
0n
#1350
1"
b11011 /
#1355
0!
0'
0>"
1B"
0<"
1@"
b10 l
b10 q
b10 3"
0D"
1n
#1400
0"
b11100 /
#1405
0n
#1450
1"
b11101 /
#1455
1!
1'
0B"
0@"
b1 l
b1 q
b1 3"
1D"
1n
#1500
0"
b11110 /
#1505
0n
#1550
1"
b11111 /
#1555
0!
0'
b0 l
b0 q
b0 3"
0D"
1n
#1600
0"
b100000 /
#1605
0n
#1650
1"
b100001 /
#1655
1n
#1700
0"
b100010 /
#1705
0n
#1750
1"
b100011 /
#1755
1n
#1800
0"
b100100 /
#1805
0n
#1850
1"
b100101 /
#1855
1n
#1900
0"
b100110 /
#1905
0n
#1950
1"
b100111 /
#1955
1n
#2000
0"
b101000 /
0+
0-
#2005
0n
#2050
1"
b101001 /
#2100
0"
b101010 /
#2150
1"
b101011 /
#2200
0"
b101100 /
#2250
1"
b101101 /
#2300
1&
0%
0"
b0 4
b11110000 (
b11110000 3
b101110 /
1,
#2350
1"
b101111 /
#2400
0"
b110000 /
#2450
1"
b110001 /
#2500
1A
1D
1H
1L
1Z
1]
1a
1e
1{
1~
1$"
1("
16"
19"
1="
1A"
0"
0:
b1111 @
0S
b1111 Y
0t
b1111 z
0/"
b1111 5"
bz (
bz 3
b110010 /
1)
0,
#2505
0E
0I
0M
0R
0C
0G
0K
b0 2
b0 7
b0 >
0O
#2550
1"
b110011 /
#2600
1""
1*"
17"
1;"
1?"
1C"
b1010 y
b1111 4"
b1010 v
b1111 1"
1u
b101 w
10"
0A
0D
0H
0L
0Z
0]
0a
0e
0$
1#
1{
0~
1$"
0("
06"
09"
0="
0A"
0"
0p
1:
b0 @
1S
b0 Y
b0 m
1t
b101 z
1/"
b0 5"
b110100 /
1.
0)
#2605
1%"
1."
1:"
1>"
1B"
1#"
b101 x
1+"
18"
1<"
1@"
b1011111 l
b1011111 q
b1111 3"
1D"
#2650
1"
b110101 /
#2670
0""
0*"
07"
0;"
0?"
0C"
b0 y
0{
0$"
b0 4"
b0 z
b0 v
b0 1"
0u
b0 w
00"
1p
0.
#2700
0"
b110110 /
#2750
1"
b110111 /
#2760
1!
1'
1+
1-
#2800
0"
b111000 /
#2850
1"
b111001 /
#2855
0%"
1)"
0."
0#
1E
0&
0#"
1'"
b101111 l
b101111 q
b10 x
0+"
b1 m
b10000000 2
b10000000 7
b1000 >
1C
b1 4
1n
15
#2900
0"
b111010 /
#2905
b10 4
b10 m
05
0n
#2950
1"
b111011 /
#2955
0)"
1."
0:"
1I
0'"
b1 x
1+"
b10111 l
b10111 q
b111 3"
08"
b11 m
b11000000 2
b11000000 7
b1100 >
1G
b11 4
1n
15
#3000
0"
b111100 /
#3005
b100 4
b100 m
05
0n
#3050
1"
b111101 /
#3055
0."
1:"
0>"
1M
b0 x
0+"
18"
b1011 l
b1011 q
b1011 3"
0<"
b101 m
b11100000 2
b11100000 7
b1110 >
1K
b101 4
1n
15
#3100
0"
b111110 /
#3105
b110 4
b110 m
05
0n
#3150
1"
b111111 /
#3155
0:"
1>"
0B"
1R
08"
1<"
b101 l
b101 q
b101 3"
0@"
b111 m
b11110000 2
b11110000 7
b1111 >
1O
b111 4
1n
15
#3200
0"
b1000000 /
#3205
1%
1$
b1000 4
b1000 m
05
0n
#3250
1"
b1000001 /
#3255
0!
0'
0>"
1B"
0<"
1@"
b10 l
b10 q
b10 3"
0D"
1n
#3300
0"
b1000010 /
#3305
0n
#3350
1"
b1000011 /
#3355
1!
1'
0B"
0@"
b1 l
b1 q
b1 3"
1D"
1n
#3400
0"
b1000100 /
#3405
0n
#3450
1"
b1000101 /
#3455
0!
0'
b0 l
b0 q
b0 3"
0D"
1n
#3500
0"
b1000110 /
#3505
0n
#3550
1"
b1000111 /
#3555
1n
#3600
0"
b1001000 /
#3605
0n
#3650
1"
b1001001 /
#3655
1n
#3700
0"
b1001010 /
#3705
0n
#3750
1"
b1001011 /
#3755
1n
#3800
0"
b1001100 /
#3805
0n
#3850
1"
b1001101 /
#3855
1n
#3860
1&
0%
b0 4
b11110000 (
b11110000 3
1,
0+
0-
#3900
0"
b1001110 /
#3905
0n
#3950
1"
b1001111 /
#4000
0"
b1010000 /
#4050
1"
b1010001 /
#4060
bz (
bz 3
0,
#4100
0"
b1010010 /
#4150
1"
b1010011 /
#4200
0"
b1010100 /
#4250
1"
b1010101 /
#4300
0"
b1010110 /
#4350
1"
b1010111 /
#4400
0"
b1011000 /
#4450
1"
b1011001 /
#4500
0"
b1011010 /
#4550
1"
b1011011 /
#4600
0"
b1011100 /
#4650
1"
b1011101 /
#4700
0"
b1011110 /
#4750
1"
b1011111 /
#4800
0"
b1100000 /
#4850
1"
b1100001 /
#4900
0"
b1100010 /
#4950
1"
b1100011 /
#5000
0"
b1100100 /
#5050
1"
b1100101 /
#5100
0"
b1100110 /
#5150
1"
b1100111 /
#5200
0"
b1101000 /
#5250
1"
b1101001 /
#5300
0"
b1101010 /
#5350
1"
b1101011 /
#5400
0"
b1101100 /
#5450
1"
b1101101 /
#5500
0"
b1101110 /
#5550
1"
b1101111 /
#5600
0"
b1110000 /
#5650
1"
b1110001 /
#5700
0"
b1110010 /
#5750
1"
b1110011 /
#5800
0"
b1110100 /
