chap_3/shift_reg_4bit.v
/*
Module name: 4 bit shift register
Author: Nguyen Thanh Phu
*/
`include "D_FF.v"

module shift_reg_4bit(
    input Clock,
    input In,
    output reg [3:0]Q
);
    d_ff dff1(.Clock(Clock), .d(In), .q(Q[0]));
    d_ff dff2(.Clock(Clock), .d(Q[0]), .d(Q[1]));
    d_ff dff3(.Clock(Clock), .d(Q[1]), .d(Q[2]));
    d_ff dff4(.Clock(Clock), .d(Q[2]), .d(Q[3]));
endmodule

chap_3/multiplexer_2_1.v
/*
Module name: Mux 2 to 1 :>
Author: Nguyen Thanh Phu
*/

module multiplexer_2_1(S, I, O);
    input S;
    input [1:0] I;
    output reg O;
    always @(S, I)
        begin
            O = (I[0] & (~S)) | (I[1] & S);
        end
endmodule

chap_3/show_wave.v
`timescale 1ns/1ns
`include "shift_reg_4bit.v"

module show_wave;
    reg[1:0] in;
    reg[4:0] index;
    wire O;

    multiplexer_2_1    multiplexer_2_1_( index[2], {index[1], index[0]}, O );


initial begin
    $dumpfile("show_wave.vcd"); 
    $dumpvars(0, show_wave);
    for (index = 5'b00000; index < 5'b10000 ; index=index+1) 
    begin
        #5;
    end
    $display("Test completed!");
end
endmodule

/*
iverilog -o show_wave.vvp show_wave.v; vvp show_wave.vvp; gtkwave show_wave.vcd
*/

chap_3/build/show_wave.vcd
$date
	Wed Mar 13 09:06:07 2024
$end
$version
	Icarus Verilog
$end
$timescale
	1ns
$end
$scope module show_wave $end
$var wire 1 ! O $end
$var reg 5 " index [4:0] $end
$scope module multiplexer_2_1_ $end
$var wire 2 # I [1:0] $end
$var wire 1 $ S $end
$var reg 1 ! O $end
$upscope $end
$upscope $end
$enddefinitions $end
$comment Show the parameter values. $end
$dumpall
$end
#0
$dumpvars
0$
b0 #
b0 "
0!
$end
#5
1!
b1 #
b1 "
#10
0!
b10 #
b10 "
#15
1!
b11 #
b11 "
#20
0!
1$
b0 #
b100 "
#25
b1 #
b101 "
#30
1!
b10 #
b110 "
#35
b11 #
b111 "
#40
0!
0$
b0 #
b1000 "
#45
1!
b1 #
b1001 "
#50
0!
b10 #
b1010 "
#55
1!
b11 #
b1011 "
#60
0!
1$
b0 #
b1100 "
#65
b1 #
b1101 "
#70
1!
b10 #
b1110 "
#75
b11 #
b1111 "
#80
0!
0$
b0 #
b10000 "
